<?xml version="1.0" encoding="utf-8" ?><dwsync><file name="MK2 Baraka.png" server="sftp.cascadia.edu//student/bit/bit271/henrylngoy/" local="3452037779" remote="319783739097111178" Dst="-1" /><file name="MK2 Jax.png" server="sftp.cascadia.edu//student/bit/bit271/henrylngoy/" local="3452037971" remote="319783739097111178" Dst="-1" /><file name="MK2 Johnny Cage.png" server="sftp.cascadia.edu//student/bit/bit271/henrylngoy/" local="3452035886" remote="319783739097111178" Dst="-1" /><file name="MK2 Kitana.png" server="sftp.cascadia.edu//student/bit/bit271/henrylngoy/" local="3452037400" remote="319783739097111178" Dst="-1" /><file name="MK2 Kung Lao.png" server="sftp.cascadia.edu//student/bit/bit271/henrylngoy/" local="3452035796" remote="319783739097111178" Dst="-1" /><file name="MK2 Mileena.png" server="sftp.cascadia.edu//student/bit/bit271/henrylngoy/" local="3452037700" remote="319783739097111178" Dst="-1" /><file name="MK2 Rayden.png" server="sftp.cascadia.edu//student/bit/bit271/henrylngoy/" local="3452037937" remote="319783739097111178" Dst="-1" /><file name="MK2 Reptile.png" server="sftp.cascadia.edu//student/bit/bit271/henrylngoy/" local="3452037249" remote="319783739097111178" Dst="-1" /><file name="MK2 Scorpion.png" server="sftp.cascadia.edu//student/bit/bit271/henrylngoy/" local="3452037814" remote="319783739097111178" Dst="-1" /><file name="MK2 Shang Tsung.png" server="sftp.cascadia.edu//student/bit/bit271/henrylngoy/" local="3452037364" remote="319783739097111178" Dst="-1" /><file name="MK2 Sub Zero.png" server="sftp.cascadia.edu//student/bit/bit271/henrylngoy/" local="3452037309" remote="319783739097111179" Dst="-1" /></dwsync>